crc32_32/test.v
`timescale 1ns/1ps

module Test();

reg clk;
reg rst_n;
wire [1:0] check_status;

initial begin
    $dumpfile("wave.vcd");
    $dumpvars(0, Test);
    clk = 0;
    forever begin
        #50 clk = ~clk;
    end
end

initial begin
    rst_n = 0;
    #220 rst_n = 1;

    #2000 $finish;
end

crc32_check uut(
    .clk(clk),
    .rst_n(rst_n),
    .check_status(check_status)
);

endmodule

module crc32_check(
    input wire clk,
    input wire rst_n,
    output reg [1:0] check_status
);
parameter INVALID = 2'b00;
parameter RUNNING = 2'b01;
parameter PASSED = 2'b10;
parameter FAILED = 2'b11;

reg [31:0] data [0:7];

reg data_in_valid;
reg [31:0] data_in;
wire [31:0] next_crc32;

integer i;

initial begin
    $readmemh("data.txt", data);
    for(i=0; i<=7; i=i+1) begin
        $display("data[%1d] = 0x%08x", i, data[i]);
    end
end

always @ (posedge clk) begin
    if(!rst_n) begin
        check_status <= INVALID;
        data_in_valid <= 1'b0;
        i <= 0;
    end
    else if(i<8) begin
        check_status <= RUNNING;
        data_in_valid <= 1'b1;
        data_in <= data[i];
        i <= i + 1;
    end
    else begin
        data_in_valid <= 1'b0;
        check_status <= (next_crc32==32'd0)?(PASSED):(FAILED);
    end
end

crc32_32 uut(
        .clk(clk),
        .rst_n(rst_n),
        .data_in_valid(data_in_valid),
        .data_in(data_in),
        .next_crc32(next_crc32)
);


endmodule

module crc32_32 (
    input wire clk,
    input wire rst_n,
    input wire data_in_valid,
    input wire [31:0] data_in,
    output reg [31:0] next_crc32
);

wire [31:0] d;
wire [31:0] c;

assign d = data_in;
assign c = next_crc32;

always @(posedge clk) begin
    if(!rst_n) begin
        next_crc32 = 32'hffffffff;
    end
    else if(data_in_valid) begin
        next_crc32[ 0] <=   d[31] ^ d[30] ^ d[29] ^ d[28] ^ d[26] ^ d[25] ^ d[24] ^ d[16] ^ d[12] ^ d[10] ^ 
                            d[ 9] ^ d[ 6] ^ d[ 0] ^ c[ 0] ^ c[ 6] ^ c[ 9] ^ c[10] ^ c[12] ^ c[16] ^ c[24] ^ 
                            c[25] ^ c[26] ^ c[28] ^ c[29] ^ c[30] ^ c[31];

        next_crc32[ 1] <=   d[28] ^ d[27] ^ d[24] ^ d[17] ^ d[16] ^ d[13] ^ d[12] ^ d[11] ^ d[ 9] ^ d[ 7] ^ 
                            d[ 6] ^ d[ 1] ^ d[ 0] ^ c[ 0] ^ c[ 1] ^ c[ 6] ^ c[ 7] ^ c[ 9] ^ c[11] ^ c[12] ^ 
                            c[13] ^ c[16] ^ c[17] ^ c[24] ^ c[27] ^ c[28];

        next_crc32[ 2] <=   d[31] ^ d[30] ^ d[26] ^ d[24] ^ d[18] ^ d[17] ^ d[16] ^ d[14] ^ d[13] ^ d[ 9] ^ 
                            d[ 8] ^ d[ 7] ^ d[ 6] ^ d[ 2] ^ d[ 1] ^ d[ 0] ^ c[ 0] ^ c[ 1] ^ c[ 2] ^ c[ 6] ^ 
                            c[ 7] ^ c[ 8] ^ c[ 9] ^ c[13] ^ c[14] ^ c[16] ^ c[17] ^ c[18] ^ c[24] ^ c[26] ^ 
                            c[30] ^ c[31];

        next_crc32[ 3] <=   d[31] ^ d[27] ^ d[25] ^ d[19] ^ d[18] ^ d[17] ^ d[15] ^ d[14] ^ d[10] ^ d[ 9] ^ 
                            d[ 8] ^ d[ 7] ^ d[ 3] ^ d[ 2] ^ d[ 1] ^ c[ 1] ^ c[ 2] ^ c[ 3] ^ c[ 7] ^ c[ 8] ^ 
                            c[ 9] ^ c[10] ^ c[14] ^ c[15] ^ c[17] ^ c[18] ^ c[19] ^ c[25] ^ c[27] ^ c[31];

        next_crc32[ 4] <=   d[31] ^ d[30] ^ d[29] ^ d[25] ^ d[24] ^ d[20] ^ d[19] ^ d[18] ^ d[15] ^ d[12] ^ 
                            d[11] ^ d[ 8] ^ d[ 6] ^ d[ 4] ^ d[ 3] ^ d[ 2] ^ d[ 0] ^ c[ 0] ^ c[ 2] ^ c[ 3] ^ 
                            c[ 4] ^ c[ 6] ^ c[ 8] ^ c[11] ^ c[12] ^ c[15] ^ c[18] ^ c[19] ^ c[20] ^ c[24] ^ 
                            c[25] ^ c[29] ^ c[30] ^ c[31];

        next_crc32[ 5] <=   d[29] ^ d[28] ^ d[24] ^ d[21] ^ d[20] ^ d[19] ^ d[13] ^ d[10] ^ d[ 7] ^ d[ 6] ^ 
                            d[ 5] ^ d[ 4] ^ d[ 3] ^ d[ 1] ^ d[ 0] ^ c[ 0] ^ c[ 1] ^ c[ 3] ^ c[ 4] ^ c[ 5] ^ 
                            c[ 6] ^ c[ 7] ^ c[10] ^ c[13] ^ c[19] ^ c[20] ^ c[21] ^ c[24] ^ c[28] ^ c[29];

        next_crc32[ 6] <=   d[30] ^ d[29] ^ d[25] ^ d[22] ^ d[21] ^ d[20] ^ d[14] ^ d[11] ^ d[ 8] ^ d[ 7] ^ 
                            d[ 6] ^ d[ 5] ^ d[ 4] ^ d[ 2] ^ d[ 1] ^ c[ 1] ^ c[ 2] ^ c[ 4] ^ c[ 5] ^ c[ 6] ^ 
                            c[ 7] ^ c[ 8] ^ c[11] ^ c[14] ^ c[20] ^ c[21] ^ c[22] ^ c[25] ^ c[29] ^ c[30];

        next_crc32[ 7] <=   d[29] ^ d[28] ^ d[25] ^ d[24] ^ d[23] ^ d[22] ^ d[21] ^ d[16] ^ d[15] ^ d[10] ^ 
                            d[ 8] ^ d[ 7] ^ d[ 5] ^ d[ 3] ^ d[ 2] ^ d[ 0] ^ c[ 0] ^ c[ 2] ^ c[ 3] ^ c[ 5] ^ 
                            c[ 7] ^ c[ 8] ^ c[10] ^ c[15] ^ c[16] ^ c[21] ^ c[22] ^ c[23] ^ c[24] ^ c[25] ^ 
                            c[28] ^ c[29];

        next_crc32[ 8] <=   d[31] ^ d[28] ^ d[23] ^ d[22] ^ d[17] ^ d[12] ^ d[11] ^ d[10] ^ d[ 8] ^ d[ 4] ^ 
                            d[ 3] ^ d[ 1] ^ d[ 0] ^ c[ 0] ^ c[ 1] ^ c[ 3] ^ c[ 4] ^ c[ 8] ^ c[10] ^ c[11] ^ 
                            c[12] ^ c[17] ^ c[22] ^ c[23] ^ c[28] ^ c[31];

        next_crc32[ 9] <=   d[29] ^ d[24] ^ d[23] ^ d[18] ^ d[13] ^ d[12] ^ d[11] ^ d[ 9] ^ d[ 5] ^ d[ 4] ^ 
                            d[ 2] ^ d[ 1] ^ c[ 1] ^ c[ 2] ^ c[ 4] ^ c[ 5] ^ c[ 9] ^ c[11] ^ c[12] ^ c[13] ^ 
                            c[18] ^ c[23] ^ c[24] ^ c[29];

        next_crc32[10] <=   d[31] ^ d[29] ^ d[28] ^ d[26] ^ d[19] ^ d[16] ^ d[14] ^ d[13] ^ d[ 9] ^ d[ 5] ^ 
                            d[ 3] ^ d[ 2] ^ d[ 0] ^ c[ 0] ^ c[ 2] ^ c[ 3] ^ c[ 5] ^ c[ 9] ^ c[13] ^ c[14] ^ 
                            c[16] ^ c[19] ^ c[26] ^ c[28] ^ c[29] ^ c[31];

        next_crc32[11] <=   d[31] ^ d[28] ^ d[27] ^ d[26] ^ d[25] ^ d[24] ^ d[20] ^ d[17] ^ d[16] ^ d[15] ^ 
                            d[14] ^ d[12] ^ d[ 9] ^ d[ 4] ^ d[ 3] ^ d[ 1] ^ d[ 0] ^ c[ 0] ^ c[ 1] ^ c[ 3] ^ 
                            c[ 4] ^ c[ 9] ^ c[12] ^ c[14] ^ c[15] ^ c[16] ^ c[17] ^ c[20] ^ c[24] ^ c[25] ^ 
                            c[26] ^ c[27] ^ c[28] ^ c[31];

        next_crc32[12] <=   d[31] ^ d[30] ^ d[27] ^ d[24] ^ d[21] ^ d[18] ^ d[17] ^ d[15] ^ d[13] ^ d[12] ^ 
                            d[ 9] ^ d[ 6] ^ d[ 5] ^ d[ 4] ^ d[ 2] ^ d[ 1] ^ d[ 0] ^ c[ 0] ^ c[ 1] ^ c[ 2] ^ 
                            c[ 4] ^ c[ 5] ^ c[ 6] ^ c[ 9] ^ c[12] ^ c[13] ^ c[15] ^ c[17] ^ c[18] ^ c[21] ^ 
                            c[24] ^ c[27] ^ c[30] ^ c[31];

        next_crc32[13] <=   d[31] ^ d[28] ^ d[25] ^ d[22] ^ d[19] ^ d[18] ^ d[16] ^ d[14] ^ d[13] ^ d[10] ^ 
                            d[ 7] ^ d[ 6] ^ d[ 5] ^ d[ 3] ^ d[ 2] ^ d[ 1] ^ c[ 1] ^ c[ 2] ^ c[ 3] ^ c[ 5] ^
                            c[ 6] ^ c[ 7] ^ c[10] ^ c[13] ^ c[14] ^ c[16] ^ c[18] ^ c[19] ^ c[22] ^ c[25] ^ 
                            c[28] ^ c[31];
        next_crc32[14] <=   d[29] ^ d[26] ^ d[23] ^ d[20] ^ d[19] ^ d[17] ^ d[15] ^ d[14] ^ d[11] ^ d[ 8] ^ 
                            d[ 7] ^ d[ 6] ^ d[ 4] ^ d[ 3] ^ d[ 2] ^ c[ 2] ^ c[ 3] ^ c[ 4] ^ c[ 6] ^ c[ 7] ^ 
                            c[ 8] ^ c[11] ^ c[14] ^ c[15] ^ c[17] ^ c[19] ^ c[20] ^ c[23] ^ c[26] ^ c[29];

        next_crc32[15] <=   d[30] ^ d[27] ^ d[24] ^ d[21] ^ d[20] ^ d[18] ^ d[16] ^ d[15] ^ d[12] ^ d[ 9] ^ 
                            d[ 8] ^ d[ 7] ^ d[ 5] ^ d[ 4] ^ d[ 3] ^ c[ 3] ^ c[ 4] ^ c[ 5] ^ c[ 7] ^ c[ 8] ^ 
                            c[ 9] ^ c[12] ^ c[15] ^ c[16] ^ c[18] ^ c[20] ^ c[21] ^ c[24] ^ c[27] ^ c[30];

        next_crc32[16] <=   d[30] ^ d[29] ^ d[26] ^ d[24] ^ d[22] ^ d[21] ^ d[19] ^ d[17] ^ d[13] ^ d[12] ^ 
                            d[ 8] ^ d[ 5] ^ d[ 4] ^ d[ 0] ^ c[ 0] ^ c[ 4] ^ c[ 5] ^ c[ 8] ^ c[12] ^ c[13] ^ 
                            c[17] ^ c[19] ^ c[21] ^ c[22] ^ c[24] ^ c[26] ^ c[29] ^ c[30];
                            
        next_crc32[17] <=   d[31] ^ d[30] ^ d[27] ^ d[25] ^ d[23] ^ d[22] ^ d[20] ^ d[18] ^ d[14] ^ d[13] ^ 
                            d[ 9] ^ d[ 6] ^ d[ 5] ^ d[ 1] ^ c[ 1] ^ c[ 5] ^ c[ 6] ^ c[ 9] ^ c[13] ^ c[14] ^ 
                            c[18] ^ c[20] ^ c[22] ^ c[23] ^ c[25] ^ c[27] ^ c[30] ^ c[31];

        next_crc32[18] <=   d[31] ^ d[28] ^ d[26] ^ d[24] ^ d[23] ^ d[21] ^ d[19] ^ d[15] ^ d[14] ^ d[10] ^ 
                            d[ 7] ^ d[ 6] ^ d[ 2] ^ c[ 2] ^ c[ 6] ^ c[ 7] ^ c[10] ^ c[14] ^ c[15] ^ c[19] ^ 
                            c[21] ^ c[23] ^ c[24] ^ c[26] ^ c[28] ^ c[31];

        next_crc32[19] <=   d[29] ^ d[27] ^ d[25] ^ d[24] ^ d[22] ^ d[20] ^ d[16] ^ d[15] ^ d[11] ^ d[ 8] ^ 
                            d[ 7] ^ d[ 3] ^ c[ 3] ^ c[ 7] ^ c[ 8] ^ c[11] ^ c[15] ^ c[16] ^ c[20] ^ c[22] ^ 
                            c[24] ^ c[25] ^ c[27] ^ c[29];

        next_crc32[20] <=   d[30] ^ d[28] ^ d[26] ^ d[25] ^ d[23] ^ d[21] ^ d[17] ^ d[16] ^ d[12] ^ d[ 9] ^ 
                            d[ 8] ^ d[ 4] ^ c[ 4] ^ c[ 8] ^ c[ 9] ^ c[12] ^ c[16] ^ c[17] ^ c[21] ^ c[23] ^ 
                            c[25] ^ c[26] ^ c[28] ^ c[30];

        next_crc32[21] <=   d[31] ^ d[29] ^ d[27] ^ d[26] ^ d[24] ^ d[22] ^ d[18] ^ d[17] ^ d[13] ^ d[10] ^ 
                            d[ 9] ^ d[ 5] ^ c[ 5] ^ c[ 9] ^ c[10] ^ c[13] ^ c[17] ^ c[18] ^ c[22] ^ c[24] ^ 
                            c[26] ^ c[27] ^ c[29] ^ c[31];

        next_crc32[22] <=   d[31] ^ d[29] ^ d[27] ^ d[26] ^ d[24] ^ d[23] ^ d[19] ^ d[18] ^ d[16] ^ d[14] ^ 
                            d[12] ^ d[11] ^ d[ 9] ^ d[ 0] ^ c[ 0] ^ c[ 9] ^ c[11] ^ c[12] ^ c[14] ^ c[16] ^ 
                            c[18] ^ c[19] ^ c[23] ^ c[24] ^ c[26] ^ c[27] ^ c[29] ^ c[31];

        next_crc32[23] <=   d[31] ^ d[29] ^ d[27] ^ d[26] ^ d[20] ^ d[19] ^ d[17] ^ d[16] ^ d[15] ^ d[13] ^ 
                            d[ 9] ^ d[ 6] ^ d[ 1] ^ d[ 0] ^ c[ 0] ^ c[ 1] ^ c[ 6] ^ c[ 9] ^ c[13] ^ c[15] ^ 
                            c[16] ^ c[17] ^ c[19] ^ c[20] ^ c[26] ^ c[27] ^ c[29] ^ c[31];

        next_crc32[24] <=   d[30] ^ d[28] ^ d[27] ^ d[21] ^ d[20] ^ d[18] ^ d[17] ^ d[16] ^ d[14] ^ d[10] ^ 
                            d[ 7] ^ d[ 2] ^ d[ 1] ^ c[ 1] ^ c[ 2] ^ c[ 7] ^ c[10] ^ c[14] ^ c[16] ^ c[17] ^ 
                            c[18] ^ c[20] ^ c[21] ^ c[27] ^ c[28] ^ c[30];

        next_crc32[25] <=   d[31] ^ d[29] ^ d[28] ^ d[22] ^ d[21] ^ d[19] ^ d[18] ^ d[17] ^ d[15] ^ d[11] ^ 
                            d[ 8] ^ d[ 3] ^ d[ 2] ^ c[ 2] ^ c[ 3] ^ c[ 8] ^ c[11] ^ c[15] ^ c[17] ^ c[18] ^ 
                            c[19] ^ c[21] ^ c[22] ^ c[28] ^ c[29] ^ c[31];

        next_crc32[26] <=   d[31] ^ d[28] ^ d[26] ^ d[25] ^ d[24] ^ d[23] ^ d[22] ^ d[20] ^ d[19] ^ d[18] ^ 
                            d[10] ^ d[ 6] ^ d[ 4] ^ d[ 3] ^ d[ 0] ^ c[ 0] ^ c[ 3] ^ c[ 4] ^ c[ 6] ^ c[10] ^ 
                            c[18] ^ c[19] ^ c[20] ^ c[22] ^ c[23] ^ c[24] ^ c[25] ^ c[26] ^ c[28] ^ c[31];

        next_crc32[27] <=   d[29] ^ d[27] ^ d[26] ^ d[25] ^ d[24] ^ d[23] ^ d[21] ^ d[20] ^ d[19] ^ d[11] ^ 
                            d[ 7] ^ d[ 5] ^ d[ 4] ^ d[ 1] ^ c[ 1] ^ c[ 4] ^ c[ 5] ^ c[ 7] ^ c[11] ^ c[19] ^ 
                            c[20] ^ c[21] ^ c[23] ^ c[24] ^ c[25] ^ c[26] ^ c[27] ^ c[29];

        next_crc32[28] <=   d[30] ^ d[28] ^ d[27] ^ d[26] ^ d[25] ^ d[24] ^ d[22] ^ d[21] ^ d[20] ^ d[12] ^ 
                            d[ 8] ^ d[ 6] ^ d[ 5] ^ d[ 2] ^ c[ 2] ^ c[ 5] ^ c[ 6] ^ c[ 8] ^ c[12] ^ c[20] ^ 
                            c[21] ^ c[22] ^ c[24] ^ c[25] ^ c[26] ^ c[27] ^ c[28] ^ c[30];

        next_crc32[29] <=   d[31] ^ d[29] ^ d[28] ^ d[27] ^ d[26] ^ d[25] ^ d[23] ^ d[22] ^ d[21] ^ d[13] ^ 
                            d[ 9] ^ d[ 7] ^ d[ 6] ^ d[ 3] ^ c[ 3] ^ c[ 6] ^ c[ 7] ^ c[ 9] ^ c[13] ^ c[21] ^ 
                            c[22] ^ c[23] ^ c[25] ^ c[26] ^ c[27] ^ c[28] ^ c[29] ^ c[31];

        next_crc32[30] <=   d[30] ^ d[29] ^ d[28] ^ d[27] ^ d[26] ^ d[24] ^ d[23] ^ d[22] ^ d[14] ^ d[10] ^ 
                            d[ 8] ^ d[ 7] ^ d[ 4] ^ c[ 4] ^ c[ 7] ^ c[ 8] ^ c[10] ^ c[14] ^ c[22] ^ c[23] ^ 
                            c[24] ^ c[26] ^ c[27] ^ c[28] ^ c[29] ^ c[30];

        next_crc32[31] <=   d[31] ^ d[30] ^ d[29] ^ d[28] ^ d[27] ^ d[25] ^ d[24] ^ d[23] ^ d[15] ^ d[11] ^ 
                            d[ 9] ^ d[ 8] ^ d[ 5] ^ c[ 5] ^ c[ 8] ^ c[ 9] ^ c[11] ^ c[15] ^ c[23] ^ c[24] ^ 
                            c[25] ^ c[27] ^ c[28] ^ c[29] ^ c[30] ^ c[31];
    end
end

endmodule

wave.vcd
$date
	Fri Aug 21 11:29:03 2020
$end
$version
	Icarus Verilog
$end
$timescale
	1ps
$end
$scope module Test $end
$var wire 2 ! check_status [1:0] $end
$var reg 1 " clk $end
$var reg 1 # rst_n $end
$scope module uut $end
$var wire 1 " clk $end
$var wire 1 # rst_n $end
$var wire 32 $ next_crc32 [31:0] $end
$var reg 2 % check_status [1:0] $end
$var reg 32 & data_in [31:0] $end
$var reg 1 ' data_in_valid $end
$var integer 32 ( i [31:0] $end
$scope module uut $end
$var wire 32 ) c [31:0] $end
$var wire 1 " clk $end
$var wire 32 * d [31:0] $end
$var wire 32 + data_in [31:0] $end
$var wire 1 ' data_in_valid $end
$var wire 1 # rst_n $end
$var reg 32 , next_crc32 [31:0] $end
$upscope $end
$upscope $end
$upscope $end
$enddefinitions $end
#0
$dumpvars
bx ,
bx +
bx *
bx )
b1000 (
x'
bx &
bx %
bx $
0#
0"
bx !
$end
#50000
b0 (
0'
b0 !
b0 %
b11111111111111111111111111111111 )
b11111111111111111111111111111111 $
b11111111111111111111111111111111 ,
1"
#100000
0"
#150000
1"
#200000
0"
#220000
1#
#250000
b1 (
b10010001101000101011001111001 *
b10010001101000101011001111001 &
b10010001101000101011001111001 +
1'
b1 !
b1 %
1"
#300000
0"
#350000
b10 (
b10100001101000101010001110100100 *
b10100001101000101010001110100100 &
b10100001101000101010001110100100 +
b11011011010010111001011110011100 )
b11011011010010111001011110011100 $
b11011011010010111001011110011100 ,
1"
#400000
0"
#450000
b10100000100001110111110101111111 )
b10100000100001110111110101111111 $
b10100000100001110111110101111111 ,
b11 (
b10110001101100101011001110110100 *
b10110001101100101011001110110100 &
b10110001101100101011001110110100 +
1"
#500000
0"
#550000
b100 (
b11000001110000101100001111000100 *
b11000001110000101100001111000100 &
b11000001110000101100001111000100 +
b11010001110010011110001011000111 )
b11010001110010011110001011000111 $
b11010001110010011110001011000111 ,
1"
#600000
0"
#650000
b100010000010110110100110001 )
b100010000010110110100110001 $
b100010000010110110100110001 ,
b101 (
b11010001110100101101001111010100 *
b11010001110100101101001111010100 &
b11010001110100101101001111010100 +
1"
#700000
0"
#750000
b110 (
b11100001111000101110001111100100 *
b11100001111000101110001111100100 &
b11100001111000101110001111100100 +
b11011100010000001110110001101011 )
b11011100010000001110110001101011 $
b11011100010000001110110001101011 ,
1"
#800000
0"
#850000
b1111100101110011100111111111111 )
b1111100101110011100111111111111 $
b1111100101110011100111111111111 ,
b111 (
b11110001111100101111001111110100 *
b11110001111100101111001111110100 &
b11110001111100101111001111110100 +
1"
#900000
0"
#950000
b1000 (
b10011100010010101001001111001110 *
b10011100010010101001001111001110 &
b10011100010010101001001111001110 +
b1010001110001101100011101111011 )
b1010001110001101100011101111011 $
b1010001110001101100011101111011 ,
1"
#1000000
0"
#1050000
b1110101101111100100011010110111 )
b1110101101111100100011010110111 $
b1110101101111100100011010110111 ,
b11 !
b11 %
0'
1"
